opstrich/__init__.py
opstrich/invoke/__init__.py
opstrich/invoke/check.py
opstrich/invoke/openssl.py
opstrich/invoke/package.py
opstrich-0.7.0.dist-info/LICENSE
opstrich-0.7.0.dist-info/WHEEL
opstrich-0.7.0.dist-info/METADATA
opstrich-0.7.0.dist-info/RECORD
