Metadata-Version: 2.1
Name: opstrich
Version: 0.7.0
Summary: DevOps tooling, various scripts, etc.
Home-page: https://github.com/RevolutionTech/opstrich
License: ISC
Author: Lucas Connors
Author-email: lucas@revolutiontech.ca
Requires-Python: >=3.6.2,<4.0.0
Classifier: Development Status :: 2 - Pre-Alpha
Classifier: Intended Audience :: Developers
Classifier: License :: OSI Approved
Classifier: Programming Language :: Python :: 3
Classifier: Programming Language :: Python :: 3.10
Classifier: Programming Language :: Python :: 3.7
Classifier: Programming Language :: Python :: 3.8
Classifier: Programming Language :: Python :: 3.9
Classifier: Topic :: Software Development
Requires-Dist: black (==22.1.0)
Requires-Dist: invoke (>=1.4.1,<2.0.0)
Requires-Dist: isort (==5.10.1)
Requires-Dist: pyupgrade (==2.31.0)
Project-URL: Repository, https://github.com/RevolutionTech/opstrich
